docop/__init__.py
docop/cli.py
docop/config.yaml.in
docop/py.typed
docop/util.py
docop-0.7.3.dist-info/LICENSE
docop-0.7.3.dist-info/METADATA
docop-0.7.3.dist-info/WHEEL
docop-0.7.3.dist-info/entry_points.txt
docop-0.7.3.dist-info/top_level.txt
docop-0.7.3.dist-info/RECORD
